pqinfo/__init__.py
pqinfo/__main__.py
pqinfo/cli.py
pqinfo/commands/__init__.py
pqinfo/commands/base.py
pqinfo/commands/show.py
pqinfo-1.0.0.dist-info/METADATA
pqinfo-1.0.0.dist-info/WHEEL
pqinfo-1.0.0.dist-info/entry_points.txt
pqinfo-1.0.0.dist-info/top_level.txt
pqinfo-1.0.0.dist-info/RECORD
