Metadata-Version: 2.1
Name: pqinfo
Version: 1.0.0
Summary: A CLI tool to see the details of a Parquet file
Home-page: https://github.com/JayjeetAtGithub/pqinfo
Author: Jayjeet Chakraborty
Author-email: jayjeetc@ucsc.edu
License: UNLICENSE
Keywords: cli
Classifier: Intended Audience :: Developers
Classifier: Topic :: Utilities
Classifier: License :: Public Domain
Classifier: Natural Language :: English
Classifier: Operating System :: OS Independent
Classifier: Programming Language :: Python :: 2
Classifier: Programming Language :: Python :: 2.6
Classifier: Programming Language :: Python :: 2.7
Classifier: Programming Language :: Python :: 3
Classifier: Programming Language :: Python :: 3.2
Classifier: Programming Language :: Python :: 3.3
Classifier: Programming Language :: Python :: 3.4
Requires-Dist: docopt
Requires-Dist: pyarrow
Requires-Dist: pandas
Provides-Extra: test
Requires-Dist: coverage ; extra == 'test'
Requires-Dist: pytest ; extra == 'test'
Requires-Dist: pytest-cov ; extra == 'test'
